README.md
movieposters/__init__.py
movieposters/errors.py
movieposters/headers.py
movieposters/imdbapi.py
movieposters-0.0.7.dist-info/LICENSE
movieposters-0.0.7.dist-info/WHEEL
movieposters-0.0.7.dist-info/METADATA
movieposters-0.0.7.dist-info/RECORD
