Metadata-Version: 2.1
Name: movieposters
Version: 0.0.7
Summary: A simple Python package to get the link a movie's poster given its title.
Home-page: https://github.com/thomasbreydo/movieposters
License: GPL-3.0-only
Author: Thomas Breydo
Author-email: tbreydo@gmail.com
Requires-Python: >=3.8,<4.0
Classifier: Development Status :: 5 - Production/Stable
Classifier: License :: OSI Approved :: GNU General Public License v3 (GPLv3)
Classifier: Operating System :: OS Independent
Classifier: Programming Language :: Python :: 3
Classifier: Programming Language :: Python :: 3.8
Classifier: Programming Language :: Python :: 3.9
Classifier: Programming Language :: Python :: 3.10
Classifier: Programming Language :: Python :: 3.11
Requires-Dist: beautifulsoup4 (>=4.11.1,<5.0.0)
Requires-Dist: lxml (>=4.9.1,<5.0.0)
Project-URL: Repository, https://github.com/thomasbreydo/movieposters
